{
  "trend_reasoning": "均线呈现明显的多头排列，短期均线在上，长期均线在下且均呈向上发散态势，价格运行在均线系统之上，趋势结构健康。",
  "position_reasoning": "股价处于近期上涨趋势的相对高位区域，虽然整体趋势向上，但已远离前期底部平台，上方空间虽有但面临获利回吐压力。",
  "volume_reasoning": "上涨阶段伴随明显放量，近期回调过程中成交量呈现缩量态势，量价配合相对健康，未见明显的恐慌性抛盘。",
  "abnormal_move_reasoning": "在1月初出现过明显的放量拉升，确立了当前的主升趋势，且该阶段涨幅适中，主力建仓痕迹较为清晰，尚未出现明显的出货迹象。",
  "signal_reasoning": "当前处于趋势延续阶段，虽然位置偏高，但量价结构保持良好，短期均线支撑有效，具备继续上攻的潜力。",
  "scores": {
    "trend_structure": 4,
    "price_position": 3,
    "volume_behavior": 4,
    "previous_abnormal_move": 4
  },
  "total_score": 3.8,
  "signal_type": "trend_start",
  "verdict": "WATCH",
  "comment": "该股目前处于健康的多头趋势中，前期放量拉升确立了主力资金介入，近期回调缩量显示抛压有限，虽然当前位置偏高，但只要短期均线不破，仍具备波段延续潜力。",
  "code": "002879"
}